hfloader/__init__.py
hfloader/hf_loader.py
hfloader-1.0.2.dist-info/LICENSE
hfloader-1.0.2.dist-info/METADATA
hfloader-1.0.2.dist-info/WHEEL
hfloader-1.0.2.dist-info/top_level.txt
hfloader-1.0.2.dist-info/RECORD
