Metadata-Version: 2.1
Name: hfloader
Version: 1.0.2
Summary: A package that loads a tokenizer and model from the HuggingFace model hub.
Home-page: https://github.com/Solonce/HFLoader
Author: Solomon Ince
Author-email: sollyince@gmail.com
Project-URL: Bug Tracker, https://github.com/Solonce/HFLoader/issues
Classifier: Programming Language :: Python :: 3
Classifier: License :: OSI Approved :: MIT License
Classifier: Operating System :: OS Independent
Requires-Python: >=3.6
License-File: LICENSE
